{
  "default-registry": {
    "kind": "git",
    "repository": "https://github.com/microsoft/vcpkg.git",
    "baseline": "782ccc18d8b819cdef6794a6c03eb3d9f7cd04aa"
  },
  "registries": [
    {
      "kind": "git",
      "repository": "https://github.com/sunzhenkai/vcpkg-base.git",
      "baseline": "c8fb765124b777e3d474b69501c205a878d68576",
      "reference": "main",
      "packages": [
        "apollo-client",
        "aerospike-client",
        "babylon",
        "cpp-common",
        "kung-fu-panda-protocols",
        "kfpanda-cpp-sdk"
      ]
    }
  ]
}
